pyqlearning/__init__.py
pyqlearning/annealing_model.py
pyqlearning/deep_q_learning.py
pyqlearning/function_approximator.py
pyqlearning/q_learning.py
pyqlearning/annealingmodel/__init__.py
pyqlearning/annealingmodel/cost_functionable.py
pyqlearning/annealingmodel/distance_computable.py
pyqlearning/annealingmodel/quantum_monte_carlo.py
pyqlearning/annealingmodel/simulated_annealing.py
pyqlearning/annealingmodel/costfunctionable/__init__.py
pyqlearning/annealingmodel/costfunctionable/boltzmann_q_learning_cost.py
pyqlearning/annealingmodel/costfunctionable/greedy_q_learning_cost.py
pyqlearning/annealingmodel/distancecomputable/__init__.py
pyqlearning/annealingmodel/distancecomputable/cost_as_distance.py
pyqlearning/annealingmodel/distancecomputable/euclidean.py
pyqlearning/annealingmodel/simulatedannealing/__init__.py
pyqlearning/annealingmodel/simulatedannealing/adaptive_simulated_annealing.py
pyqlearning/deepqlearning/__init__.py
pyqlearning/deepqlearning/deep_q_network.py
pyqlearning/functionapproximator/__init__.py
pyqlearning/functionapproximator/cnn_fa.py
pyqlearning/functionapproximator/lstm_fa.py
pyqlearning/qlearning/__init__.py
pyqlearning/qlearning/boltzmann_q_learning.py
pyqlearning/qlearning/greedy_q_learning.py
pyqlearning/samplabledata/__init__.py
pyqlearning/samplabledata/policysampler/__init__.py
pyqlearning/samplabledata/policysampler/_mxnet/__init__.py
pyqlearning/samplabledata/policysampler/_mxnet/maze_multi_agent_policy.py
pyqlearning/samplabledata/policysampler/_mxnet/maze_policy.py
pyqlearning-1.2.5.dist-info/METADATA
pyqlearning-1.2.5.dist-info/RECORD
pyqlearning-1.2.5.dist-info/WHEEL
pyqlearning-1.2.5.dist-info/top_level.txt
