Metadata-Version: 2.1
Name: pyqlearning
Version: 1.2.5
Summary: pyqlearning is Python library to implement Reinforcement Learning and Deep Reinforcement Learning, especially for Q-Learning, Deep Q-Network, and Multi-agent Deep Q-Network which can be optimized by Annealing models such as Simulated Annealing, Adaptive Simulated Annealing, and Quantum Monte Carlo Method.
Home-page: https://github.com/accel-brain/accel-brain-code/tree/master/Reinforcement-Learning
Author: accel-brain
Author-email: info@accel-brain.co.jp
License: GPL2
Keywords: Q-Learning Deep Q-Network DQN Reinforcement Learning Boltzmann Multi-agent LSTM CNN Convolution
Platform: UNKNOWN
Classifier: Development Status :: 5 - Production/Stable
Classifier: Intended Audience :: Information Technology
Classifier: Intended Audience :: Science/Research
Classifier: Framework :: Robot Framework
Classifier: Topic :: Scientific/Engineering :: Artificial Intelligence
Classifier: License :: OSI Approved :: GNU General Public License v2 (GPLv2)
Classifier: Programming Language :: Python :: 3
Requires-Dist: numpy
Requires-Dist: pandas
